{
  "settings": {
    "model": "Grok",
    "user_id": "09",
    "life_prompt_type": "JSON",
    "demo_info": false,
    "figure": false
  },
  "give_tipi_1": [
    {
      "question": "活発で、外向的だと思う",
      "reason": "9歳の野球イベントで誰よりも声を出して努力し賞品を当てたことや、17歳のテニス部でワイワイ練習を楽しんだことから活発な面があるが、11歳で女子とのコミュニケーションが苦手になり加速したため、外向性は限定的。",
      "answer": 5
    },
    {
      "question": "他人に不満をもち、もめごとを起こしやすいと思う",
      "reason": "12歳で仲の良い友人と絶交し、思いが爆発して言い過ぎた経験はあるが、他のエピソードでは挫折を内省的に学び前向きに転換しており、もめごとを繰り返さない。",
      "answer": 2
    },
    {
      "question": "しっかりしていて、自分に厳しいと思う",
      "reason": "15歳で中学生まで勉強ができなかったが高校で努力し学年1位を取ったこと、17歳のテニス負けで後悔し練習を頑張るようになったこと、18歳の一人暮らしで自立したことから、自分に厳しく努力を続ける性格。",
      "answer": 7
    },
    {
      "question": "心配性で、うろたえやすいと思う",
      "reason": "14歳で猫が死んだショックや16歳でライン削除のショックがあったが、いずれも後悔を教訓に前向きに変え、うろたえずに冷静に対処している記述が多い。",
      "answer": 2
    },
    {
      "question": "新しいことが好きで、変わった考えをもつと思う",
      "reason": "20歳でゲームという新趣味に出会い楽しんだり、19歳で大学の友達と九州旅行をしたが、全体的に努力中心の平凡なエピソードが多く、変わった考えは見られない。",
      "answer": 4
    },
    {
      "question": "ひかえめで、おとなしいと思う",
      "reason": "11歳で彼女に振られ女子苦手が加速し、16歳で積極的になろうと思ったが、9歳のように声を出したりテニスで活動的だった面もあり、完全におとなしいわけではない。",
      "answer": 5
    },
    {
      "question": "人に気をつかう、やさしい人間だと思う",
      "reason": "14歳で猫の死に後悔し身近なものを大切にしようと思ったこと、11歳で男友達との絆が深まり今も続くこと、13歳で恋が生活を頑張らせる原動力となったことから、人に優しく気遣う。",
      "answer": 6
    },
    {
      "question": "だらしなく、うっかりしていると思う",
      "reason": "21歳で研究室に馴染めず大学に行かなくなり留年したが、そこから人生を振り返り学び直したため、だらしなさは一時的で全体的に努力家。",
      "answer": 3
    },
    {
      "question": "冷静で、気分が安定していると思う",
      "reason": "幸福度が-100や-90の挫折（12歳絶交、14歳猫死、16歳ライン削除）でも、後から「必要な出来事」「いい出来事だった」と冷静にポジティブに振り返るパターンが多く、気分安定。",
      "answer": 6
    },
    {
      "question": "発想力に欠けた、平凡な人間だと思う",
      "reason": "20歳まで趣味がなく、勉強やスポーツで地道に努力するエピソードが中心で、創造的な発想や変わった考えの記述がなく、平凡な道を努力で進むタイプ。",
      "answer": 6
    }
  ],
  "give_tipi_2": [
    {
      "question": "活発で、外向的だと思う",
      "reason": "9歳の野球イベントで誰よりも声を出して努力し報われた経験から積極性はあるが、11歳で女子に嫌われコミュニケーションが苦手になったり、21歳で研究室に馴染めず大学に行かなくなったため、内向的な面も強く、外向的とは言い難い。",
      "answer": 4
    },
    {
      "question": "他人に不満をもち、もめごとを起こしやすいと思う",
      "reason": "12歳で仲の良かった友人とたまりにたまった思いが爆発して絶交し、言い過ぎだったと反省した経験があるが、それ以外では男友達との絆を深めたり（11歳）、ゲームで新しい友達を作ったり（20歳）と基本的に調和を重視している。",
      "answer": 3
    },
    {
      "question": "しっかりしていて、自分に厳しいと思う",
      "reason": "15歳で中学生時代は勉強ができなかったが高校で努力し学年一位を取った、17歳のテニス負けで練習をより頑張るようになった、18歳の一人暮らしと大学合格で自立と努力の成果を実感し、自分に厳しく成長を求める性格が確立した。",
      "answer": 7
    },
    {
      "question": "心配性で、うろたえやすいと思う",
      "reason": "14歳で猫が死んだショックや16歳でライン削除のショック（幸福度-90）があったが、それらを勉強や積極性への糧に変え（16歳、17歳）、21歳の留年も人生を見つめ直すきっかけとしたため、うろたえずに前向きに乗り越える。",
      "answer": 2
    },
    {
      "question": "新しいことが好きで、変わった考えをもつと思う",
      "reason": "20歳でゲームという新しい趣味に出会い友達を増やした喜びや19歳の九州旅行を楽しんだが、基本的に努力や勉強、スポーツ（15歳、17歳）を重視し、変わった考えというより平凡な努力家で新しいことに特別飛びつくタイプではない。",
      "answer": 4
    },
    {
      "question": "ひかえめで、おとなしいと思う",
      "reason": "11歳で彼女に振られ女子とのコミュニケーションが苦手になり加速、16歳で積極的になろうと思ったが、9歳のイベントでは声を出したり男友達との絆を深め（11歳）たりするため、完全にひかえめではなく状況による。",
      "answer": 5
    },
    {
      "question": "人に気をつかう、やさしい人間だと思う",
      "reason": "14歳の猫の死で身近なものを大切にしようと学び、11歳で男友達との絆が深まり今も続く、13歳で恋愛が生活を頑張らせる重要性を知り、20歳で趣味共有の素晴らしさを学んだため、人間関係を大切に気遣う優しさがある。",
      "answer": 6
    },
    {
      "question": "だらしなく、うっかりしていると思う",
      "reason": "21歳で研究室に馴染めず大学に行かなくなって留年したが、それを学びの機会とし、18歳の一人暮らしで自立を身につけ、15歳以降は勉強をしっかりやり成果を出したため、だらしなさは一時的で全体的にしっかり者。",
      "answer": 3
    },
    {
      "question": "冷静で、気分が安定していると思う",
      "reason": "幸福度が-100（12歳、14歳）や-90（16歳、21歳）と大きく変動しショックを受けたが、各回で学びに変え努力を継続（16歳勉強励む、17歳練習頑張る）したため、ある程度冷静だが気分は安定せず波がある。",
      "answer": 4
    },
    {
      "question": "発想力に欠けた、平凡な人間だと思う",
      "reason": "努力で学年一位（15歳）や大学合格（18歳）を勝ち取り、ゲーム趣味（20歳）で友達作ったが、特別変わった発想より地道な努力と学びを重視（9歳、17歳、21歳）し、平凡だが着実な人間である。",
      "answer": 5
    }
  ],
  "give_tipi_3": [
    {
      "question": "活発で、外向的だと思う",
      "reason": "9歳の野球イベントで誰よりも声を出しバットが当たった経験から努力的な積極性があり、11歳で男友達の絆が深まり今も続くなど社交性はあるが、11歳の振られ体験や16歳のライン削除で女子とのコミュニケーションが苦手になり内向寄りに変化したため、どちらでもない程度。",
      "answer": 4
    },
    {
      "question": "他人に不満をもち、もめごとを起こしやすいと思う",
      "reason": "12歳で仲良し友人と絶交し「たまりにたまった思いが爆発」したように過去に不満爆発の経験はあるが、それ以降コミュニケーションの難しさを学び成長しており、他のエピソードでは友達関係が続き絆を維持しているため、少し違うと思う。",
      "answer": 3
    },
    {
      "question": "しっかりしていて、自分に厳しいと思う",
      "reason": "15歳で中学生までの苦手克服のため勉強努力し学年1位、17歳テニス負けで「もっと練習を頑張る」ようになり、18歳一人暮らしで自立し大学合格の成果を得たように、努力と自己反省を繰り返す自分に厳しい姿勢が一貫している。",
      "answer": 7
    },
    {
      "question": "心配性で、うろたえやすいと思う",
      "reason": "14歳猫の死で「もっと大切にしてやれば」と後悔しショックを受け、16歳ライン削除で大ショックだったが、いずれも勉強や前向きに転換しており、21歳留年でも人生を見つめ直す冷静さが見られ、どちらでもない。",
      "answer": 4
    },
    {
      "question": "新しいことが好きで、変わった考えをもつと思う",
      "reason": "19歳九州旅行や20歳ゲーム趣味で新しい楽しみを発見したが、他のエピソードは努力中心の平凡な勉強・スポーツ・恋愛が多く、特別変わった発想は見られず少し違う。",
      "answer": 3
    },
    {
      "question": "ひかえめで、おとなしいと思う",
      "reason": "10歳恋愛で会話克服するも11歳振られで女子苦手加速、16歳で「次はもっと積極的になろう」と反省するように、積極性が不足し慎重・控えめな面が強い一方、9歳の声援や男友達多さで完全に内気ではない。",
      "answer": 5
    },
    {
      "question": "人に気をつかう、やさしい人間だと思う",
      "reason": "14歳猫の死で「身近にあるものをもっと大切に」、11歳男友達絆が続き、13歳恋愛で生活頑張れたように、他者や絆を重視し気遣う優しさが育ち、12歳絶交も「言い過ぎだった」と反省する姿勢からまあまあそう思う。",
      "answer": 6
    },
    {
      "question": "だらしなく、うっかりしていると思う",
      "reason": "21歳大学行かず留年したが「学びなおしをし人生を見つめなおす良いきっかけ」と前向きに捉え、18歳一人暮らしで自立したように全体的に努力家でだらしなさは少なく、おおよそ違う。",
      "answer": 2
    },
    {
      "question": "冷静で、気分が安定していると思う",
      "reason": "幸福度が12歳・14歳-100、16歳-90、17歳-75、21歳-93と挫折で大きく揺れショックを受けやすいが、毎回努力や学びに転換する回復力はあるため、少し違う。",
      "answer": 3
    },
    {
      "question": "発想力に欠けた、平凡な人間だと思う",
      "reason": "努力で勉強1位や大学合格、テニス・ゲームなどの普通の趣味中心で特別な創造性は見られず、20歳「趣味を他人と共有する素晴らしさ」を学んだ平凡な喜びを重視するため、少しそう思う。",
      "answer": 5
    }
  ],
  "give_pvq_1": [
    {
      "question": "ある人は、自分なりの意見を形作ることを大事にしている。",
      "reason": "21歳のエピソードで研究室に合わず大学に行かなくなり、人生を見つめ直すきっかけになったことから、自分の人生を自分で考え直すことを重視するようになった。15歳で努力の結果学年1位を取り勉強好きになった経験から、自分のやり方で成功を掴む価値観が確立した。",
      "answer": 5
    },
    {
      "question": "ある人は、自分の国が安全で安定していることを大事にしている。",
      "reason": "人生体験に国や安全に関する直接的な言及がなく、個人的な努力や人間関係に焦点が当たっているため、似ていない。",
      "answer": 2
    },
    {
      "question": "ある人は、楽しい時間を過ごすことを大事にしている。",
      "reason": "19歳で大学の友達と九州旅行を楽しんだり、20歳でゲームという趣味に出会い共有の素晴らしさを学んだことから、楽しい時間を友人や趣味で過ごすことを重視する。",
      "answer": 5
    },
    {
      "question": "ある人は、人を困らせないことを大事にしている。",
      "reason": "12歳で友人と絶交し言い過ぎを後悔した経験から、コミュニケーションの難しさを学び、人付き合いに配慮するようになったが、絶対視ではない。",
      "answer": 4
    },
    {
      "question": "ある人は、社会の中で弱く傷つきやすい人々が守られることを大事にしている。",
      "reason": "社会的な弱者保護に関するエピソードがなく、個人的な経験中心のため似ていない。",
      "answer": 2
    },
    {
      "question": "ある人は、自分が言った通りに人が動くことを大事にしている。",
      "reason": "人間関係で友達の絆を深めたが（11歳）、支配的な側面はなく、むしろコミュニケーションの学び（12歳）から対等な関係を重視。",
      "answer": 1
    },
    {
      "question": "ある人は、自分が他の人より価値があるとは決して考えないことを大事にしている。",
      "reason": "15歳で学年1位を取った成功体験や18歳の大学合格で努力の成果を実感したが、謙虚さより努力を重視。",
      "answer": 3
    },
    {
      "question": "ある人は、自然を大切にすることを大事にしている。",
      "reason": "自然に関する直接的なエピソードがなく、個人的な喪失（14歳の猫）で身近なものを大切にする学びはあるが、自然全体ではない。",
      "answer": 2
    },
    {
      "question": "ある人は、誰にも恥をかかされないことを大事にしている。",
      "reason": "11歳で振られクラス女子に嫌われ、16歳でライン削除されるなど恥辱体験から積極的に変わろうとしたが、世間体より成長重視。",
      "answer": 2
    },
    {
      "question": "ある人は、いつも何か新しくやる事を探すことを大事にしている。",
      "reason": "20歳でゲームという新しい趣味に出会い、19歳で旅行など新しい経験を楽しんだが、常に探すほどではない。",
      "answer": 4
    },
    {
      "question": "ある人は、親しい人の世話をすることを大事にしている。",
      "reason": "14歳で猫の死を後悔し身近なものを大切にしようと思ったが、人間関係では友情の絆（11歳）を重視するものの世話中心ではない。",
      "answer": 4
    },
    {
      "question": "ある人は、お金がもたらす権力を手に入れることを大事にしている。",
      "reason": "お金や権力に関する言及がなく、努力や人間関係中心。",
      "answer": 1
    },
    {
      "question": "ある人は、病気を避け、健康を守ることをとても大事にしている。",
      "reason": "健康に関する直接エピソードなし。",
      "answer": 2
    },
    {
      "question": "ある人は、あらゆる人達や集団に対して寛容であることを大事にしている。",
      "reason": "11歳で女子苦手加速したが男友達絆深く、全体的に寛容とは限らず。",
      "answer": 3
    },
    {
      "question": "ある人は、規則や規定を決して破らないことを大事にしている。",
      "reason": "9歳で誰かが見てなくてもいい行いの大切さを知ったが、規則破りエピソードなし。",
      "answer": 4
    },
    {
      "question": "ある人は、自分の人生は自分で決断するということを大事にしている。",
      "reason": "18歳で一人暮らしをし自立、21歳で大学行かず人生見つめ直し。",
      "answer": 6
    },
    {
      "question": "ある人は、人生において野心をもつことを大事にしている。",
      "reason": "15歳学年1位、17歳テニスで勝ちこだわり、18歳大学合格と努力で成功を求める野心あり。",
      "answer": 5
    },
    {
      "question": "ある人は、伝統的な価値観や物の考え方を持ち続けることを大事にしている。",
      "reason": "伝統に関する言及なし、変化と学び中心。",
      "answer": 2
    },
    {
      "question": "ある人は、知り合いから絶対の信頼を置かれることを大事にしている。",
      "reason": "11歳で男友達との絆深まり今も続く、信頼できる友情を重視。",
      "answer": 5
    },
    {
      "question": "ある人は、裕福であることを大事にしている。",
      "reason": "裕福さ言及なし。",
      "answer": 1
    },
    {
      "question": "ある人は、自然を守るための活動に参加することを大事にしている。",
      "reason": "自然活動なし。",
      "answer": 1
    },
    {
      "question": "ある人は、人を決して苛立たせないことを大事にしている。",
      "reason": "12歳絶交で後悔したが、絶対避けるほどではない。",
      "answer": 3
    },
    {
      "question": "ある人は、自分の考えを確立することを大事にしている。",
      "reason": "21歳で人生見つめ直し、努力のサイクル（15歳）で自分の勉強法確立。",
      "answer": 5
    },
    {
      "question": "ある人は、世間体を守り続けることを大事にしている。",
      "reason": "恥辱体験（11歳、16歳）あるが成長に活かす。",
      "answer": 2
    },
    {
      "question": "ある人は、自分の大切な人を助けることをとても大事にしている。",
      "reason": "14歳猫後悔、友情絆（11歳）から大切な人を守る意識あり。",
      "answer": 5
    },
    {
      "question": "ある人は、自分の身が安全で守られていることを大事にしている。",
      "reason": "安全言及なし、むしろ挑戦。",
      "answer": 2
    },
    {
      "question": "ある人は、信頼され、頼られる友人となることを大事にしている。",
      "reason": "11歳男友達絆、12歳コミュニケーション学び。",
      "answer": 6
    },
    {
      "question": "ある人は、人生を刺激的にするようなリスクを負うことを大事にしている。",
      "reason": "一人暮らし（18歳）や留年（21歳）はリスクだが、刺激的リスク追求ではない。",
      "answer": 3
    },
    {
      "question": "ある人は、自分の望むことを他の人にさせる権力をもつことを大事にしている。",
      "reason": "権力志向なし。",
      "answer": 1
    },
    {
      "question": "ある人は、自立して行動を計画することを大事にしている。",
      "reason": "18歳一人暮らしで自立、大学合格努力。",
      "answer": 6
    },
    {
      "question": "ある人は、誰も見ていない時でも規則を守ることを大事にしている。",
      "reason": "9歳で誰かが見てなくてもいい行いの大切さ。",
      "answer": 6
    },
    {
      "question": "ある人は、大きな成功を収めることを大事にしている。",
      "reason": "18歳大学合格、15歳1位と成功体験重視。",
      "answer": 5
    },
    {
      "question": "ある人は、家族の習慣や宗教のしきたりに従うことを大事にしている。",
      "reason": "家族習慣言及なし。",
      "answer": 1
    },
    {
      "question": "ある人は、自分とは違う人の言うことに耳を傾け、理解する事を大事にしている。",
      "reason": "コミュニケーション学び（12歳）、女子苦手克服試み（10歳）。",
      "answer": 4
    },
    {
      "question": "ある人は、市民を守ることができる強い国に住むことを大事にしている。",
      "reason": "国関連なし。",
      "answer": 2
    },
    {
      "question": "ある人は、人生の喜びを味わうことを大事にしている。",
      "reason": "13歳恋愛で生活頑張れる、19歳旅行、20歳趣味。",
      "answer": 5
    },
    {
      "question": "ある人は、世界のすべての人々が人生において平等な機会をもつことを大事にしている。",
      "reason": "平等言及なし。",
      "answer": 2
    },
    {
      "question": "ある人は、謙虚であることを大事にしている。",
      "reason": "成功時努力を認めるが謙虚強調なし。",
      "answer": 3
    },
    {
      "question": "ある人は、物事を自分で何とかすることを大事にしている。",
      "reason": "自立（18歳）、勉強努力（15歳）。",
      "answer": 6
    },
    {
      "question": "ある人は、自身の文化に関する伝統的なしきたりを重んじることを大事にしている。",
      "reason": "文化伝統なし。",
      "answer": 1
    },
    {
      "question": "ある人は、周囲の人にやるべきことを指示する立場であることを大事にしている。",
      "reason": "指示者志向なし。",
      "answer": 1
    },
    {
      "question": "ある人は、いかなる法律も遵守することを大事にしている。",
      "reason": "法律言及なし、いい行い（9歳）程度。",
      "answer": 3
    },
    {
      "question": "ある人は、あらゆる種類の新しい経験をすることを大事にしている。",
      "reason": "旅行（19歳）、ゲーム（20歳）で新しい経験楽しむ。",
      "answer": 4
    },
    {
      "question": "ある人は、自分の富が分かる高価なものをもつことを大事にしている。",
      "reason": "富なし。",
      "answer": 1
    },
    {
      "question": "ある人は、自然環境を破壊や汚染から守ることを大事にしている。",
      "reason": "自然保護なし。",
      "answer": 1
    },
    {
      "question": "ある人は、あらゆる機会を利用して楽しむことを大事にしている。",
      "reason": "楽しい時間（19歳、20歳）重視。",
      "answer": 5
    },
    {
      "question": "ある人は、自分の大切な人が必要とする全てのことに携わることを大事にしている。",
      "reason": "大切な人助け（14歳学び）。",
      "answer": 5
    },
    {
      "question": "ある人は、自分の功績を人々が認めることを大事にしている。",
      "reason": "9歳努力報われ、18歳合格成果感じる。",
      "answer": 4
    },
    {
      "question": "ある人は、決して屈辱を与えられないことを大事にしている。",
      "reason": "屈辱受け成長。",
      "answer": 2
    },
    {
      "question": "ある人は、自分の国がすべての脅威から自国を守ることを大事にしている。",
      "reason": "国安全なし。",
      "answer": 2
    },
    {
      "question": "ある人は、決して人を怒らせないことを大事にしている。",
      "reason": "12歳絶交後悔。",
      "answer": 4
    },
    {
      "question": "ある人は、たとえ自分の知らない人であっても、誰もが公正に扱われることを大事にしている。",
      "reason": "公正言及なし。",
      "answer": 2
    },
    {
      "question": "ある人は、いかなる危険も避けることを大事にしている。",
      "reason": "リスク取る自立あり。",
      "answer": 2
    },
    {
      "question": "ある人は、今あるものに満足し、それ以上を求めないことを大事にしている。",
      "reason": "野心・努力追求。",
      "answer": 1
    },
    {
      "question": "ある人は、すべての友人や家族が自分に絶対の信頼を寄せられることを大事にしている。",
      "reason": "友情信頼（11歳）。",
      "answer": 5
    },
    {
      "question": "ある人は、やることを自分で自由に選択できることを大事にしている。",
      "reason": "自立・人生決断（18歳、21歳）。",
      "answer": 6
    },
    {
      "question": "ある人は、たとえ自分と意見が反対の立場の人であっても、その人を受け入れることを大事にしている。",
      "reason": "コミュニケーション学びあるが限定的。",
      "answer": 3
    }
  ],
  "give_pvq_2": [
    {
      "question": "ある人は、自分なりの意見を形作ることを大事にしている。",
      "reason": "21歳で研究室に馴染めず大学に行かなくなり留年したが、学び直しをして自分の人生を振り返り見つめ直したため、自分なりの意見を形成する重要性を学んだ。",
      "answer": 5
    },
    {
      "question": "ある人は、自分の国が安全で安定していることを大事にしている。",
      "reason": "人生体験に国や社会の安定に関するエピソードがなく、個人的な努力や人間関係に焦点が当たっているため、特に関心が薄い。",
      "answer": 2
    },
    {
      "question": "ある人は、楽しい時間を過ごすことを大事にしている。",
      "reason": "19歳で大学の友達と九州旅行を楽しんだり、20歳でゲームという趣味に出会い他人と共有する喜びを知ったため、楽しい時間を重視する。",
      "answer": 6
    },
    {
      "question": "ある人は、人を困らせないことを大事にしている。",
      "reason": "12歳で友人と絶交し言い過ぎたことを後悔したため、人付き合いの難しさを学び人を困らせないよう気をつけるようになった。",
      "answer": 4
    },
    {
      "question": "ある人は、社会の中で弱く傷つきやすい人々が守られることを大事にしている。",
      "reason": "社会的な弱者保護のエピソードはなく、個人的な喪失（14歳猫の死）で身近なものを大切にするようになったが、社会全体には言及なし。",
      "answer": 2
    },
    {
      "question": "ある人は、自分が言った通りに人が動くことを大事にしている。",
      "reason": "人生でリーダーシップや人を動かす権力への言及がなく、むしろ友情の絆や努力個人主義が強い。",
      "answer": 1
    },
    {
      "question": "ある人は、自分が他の人より価値があるとは決して考えないことを大事にしている。",
      "reason": "15歳で学年1位、18歳大学合格などの成功体験があるが、謙虚さを強調せず努力の成果として受け止めている。",
      "answer": 3
    },
    {
      "question": "ある人は、自然を大切にすることを大事にしている。",
      "reason": "自然に関するエピソードがなく、ペットの死（14歳）で身近な生き物を大切にするようになったが、自然全体ではない。",
      "answer": 2
    },
    {
      "question": "ある人は、誰にも恥をかかされないことを大事にしている。",
      "reason": "17歳テニス負けで悔しさを感じたが、後悔をバネに練習を頑張るようになったため、恥を避けるより成長を優先。",
      "answer": 2
    },
    {
      "question": "ある人は、いつも何か新しくやる事を探すことを大事にしている。",
      "reason": "20歳でゲームという新しい趣味に出会い友達が増え、19歳旅行など新しい経験を楽しんだため、新しさを求める。",
      "answer": 5
    },
    {
      "question": "ある人は、親しい人の世話をすることを大事にしている。",
      "reason": "14歳猫の死で「もっと大切にしてやればよかった」と後悔し、11歳で男友達との絆が深まったため、親しい人を大切にする。",
      "answer": 6
    },
    {
      "question": "ある人は、お金がもたらす権力を手に入れることを大事にしている。",
      "reason": "お金や権力への言及がなく、努力や人間関係、成功体験が中心。",
      "answer": 1
    },
    {
      "question": "ある人は、病気を避け、健康を守ることをとても大事にしている。",
      "reason": "健康や病気避けのエピソードなし。ペットの死はあるが人間の健康ではない。",
      "answer": 2
    },
    {
      "question": "ある人は、あらゆる人達や集団に対して寛容であることを大事にしている。",
      "reason": "11歳で女子に嫌われ苦手意識加速、12歳絶交など特定の人に厳しく、寛容さの学びは限定的。",
      "answer": 3
    },
    {
      "question": "ある人は、規則や規定を決して破らないことを大事にしている。",
      "reason": "9歳でイベントで声を出して努力が報われ「誰かが見てなくてもいい行い」の大切さを知ったが、規則破りなし。",
      "answer": 4
    },
    {
      "question": "ある人は、自分の人生は自分で決断するということを大事にしている。",
      "reason": "18歳一人暮らしで自立、21歳留年で人生を自分で振り返り見つめ直したため、自決を重視。",
      "answer": 6
    },
    {
      "question": "ある人は、人生において野心をもつことを大事にしている。",
      "reason": "15歳学年1位、18歳大学合格、17歳テニスで勝ちにこだわるなど、努力と成功への野心が強い。",
      "answer": 6
    },
    {
      "question": "ある人は、伝統的な価値観や物の考え方を持ち続けることを大事にしている。",
      "reason": "伝統や習慣への言及なく、新しい趣味（20歳ゲーム）や自立（18歳一人暮らし）を楽しむ。",
      "answer": 2
    },
    {
      "question": "ある人は、知り合いから絶対の信頼を置かれることを大事にしている。",
      "reason": "11歳で男友達との絆深まり今も続く、信頼される友人関係を重視。",
      "answer": 5
    },
    {
      "question": "ある人は、裕福であることを大事にしている。",
      "reason": "裕福さやお金への言及なし。大学合格などの達成が喜び。",
      "answer": 2
    },
    {
      "question": "ある人は、自然を守るための活動に参加することを大事にしている。",
      "reason": "自然保護活動のエピソードなし。",
      "answer": 1
    },
    {
      "question": "ある人は、人を決して苛立たせないことを大事にしている。",
      "reason": "12歳絶交で「言い過ぎだった」と後悔したが、苛立たせない徹底した重視ではない。",
      "answer": 3
    },
    {
      "question": "ある人は、自分の考えを確立することを大事にしている。",
      "reason": "21歳留年で自分の人生を見つめ直し、16歳ライン削除後積極的にする考えを確立。",
      "answer": 5
    },
    {
      "question": "ある人は、世間体を守り続けることを大事にしている。",
      "reason": "世間体への言及なく、個人的成長や友情重視。",
      "answer": 2
    },
    {
      "question": "ある人は、自分の大切な人を助けることをとても大事にしている。",
      "reason": "14歳猫の死で後悔、11歳友達絆、恋愛エピソードで大切な人を思う心強い。",
      "answer": 6
    },
    {
      "question": "ある人は、自分の身が安全で守られていることを大事にしている。",
      "reason": "安全への個人的言及なし。",
      "answer": 2
    },
    {
      "question": "ある人は、信頼され、頼られる友人となることを大事にしている。",
      "reason": "11歳男友達との絆が続き、20歳ゲームで友達出会い、信頼される関係を重視。",
      "answer": 6
    },
    {
      "question": "ある人は、人生を刺激的にするようなリスクを負うことを大事にしている。",
      "reason": "18歳一人暮らし、19歳旅行、20歳新趣味など新しい挑戦を楽しむが、リスク大は少ない。",
      "answer": 4
    },
    {
      "question": "ある人は、自分の望むことを他の人にさせる権力をもつことを大事にしている。",
      "reason": "権力志向なし。",
      "answer": 1
    },
    {
      "question": "ある人は、自立して行動を計画することを大事にしている。",
      "reason": "18歳一人暮らしで自立し「大人に一歩近づいた」、21歳人生見つめ直し。",
      "answer": 6
    },
    {
      "question": "ある人は、誰も見ていない時でも規則を守ることを大事にしている。",
      "reason": "9歳イベントで「誰かが見てなくてもいい行い」の大切さを知った。",
      "answer": 6
    },
    {
      "question": "ある人は、大きな成功を収めることを大事にしている。",
      "reason": "15歳学年1位、18歳大学合格で努力の成果を実感、野心強い。",
      "answer": 6
    },
    {
      "question": "ある人は、家族の習慣や宗教のしきたりに従うことを大事にしている。",
      "reason": "家族習慣や宗教の言及なし。",
      "answer": 1
    },
    {
      "question": "ある人は、自分とは違う人の言うことに耳を傾け、理解する事を大事にしている。",
      "reason": "12歳絶交でコミュニケーション難しさ学び、10歳恋愛で会話克服したが、限定的。",
      "answer": 4
    },
    {
      "question": "ある人は、市民を守ることができる強い国に住むことを大事にしている。",
      "reason": "国力への言及なし。",
      "answer": 2
    },
    {
      "question": "ある人は、人生の喜びを味わうことを大事にしている。",
      "reason": "13歳恋愛で生活頑張れる学び、19歳旅行、20歳ゲームで喜び重視。",
      "answer": 6
    },
    {
      "question": "ある人は、世界のすべての人々が人生において平等な機会をもつことを大事にしている。",
      "reason": "平等機会の社会観なし、個人努力中心。",
      "answer": 2
    },
    {
      "question": "ある人は、謙虚であることを大事にしている。",
      "reason": "成功体験（15歳1位、18歳合格）で努力を誇るが、謙虚強調なし。",
      "answer": 3
    },
    {
      "question": "ある人は、物事を自分で何とかすることを大事にしている。",
      "reason": "18歳一人暮らし、21歳留年克服で自力解決。",
      "answer": 6
    },
    {
      "question": "ある人は、自身の文化に関する伝統的なしきたりを重んじることを大事にしている。",
      "reason": "文化伝統なし。",
      "answer": 1
    },
    {
      "question": "ある人は、周囲の人にやるべきことを指示する立場であることを大事にしている。",
      "reason": "指示者志向なし。",
      "answer": 1
    },
    {
      "question": "ある人は、いかなる法律も遵守することを大事にしている。",
      "reason": "法律遵守の具体例なしが、9歳いい行いの価値観から推測可能。",
      "answer": 4
    },
    {
      "question": "ある人は、あらゆる種類の新しい経験をすることを大事にしている。",
      "reason": "19歳旅行、20歳ゲーム新趣味など新しい経験積極的。",
      "answer": 5
    },
    {
      "question": "ある人は、自分の富が分かる高価なものをもつことを大事にしている。",
      "reason": "富示威なし。",
      "answer": 1
    },
    {
      "question": "ある人は、自然環境を破壊や汚染から守ることを大事にしている。",
      "reason": "環境保護なし。",
      "answer": 1
    },
    {
      "question": "ある人は、あらゆる機会を利用して楽しむことを大事にしている。",
      "reason": "楽しい時間（旅行、ゲーム、恋愛）を積極的に楽しむ。",
      "answer": 6
    },
    {
      "question": "ある人は、自分の大切な人が必要とする全てのことに携わることを大事にしている。",
      "reason": "14歳猫後悔、恋愛・友情で大切な人重視。",
      "answer": 5
    },
    {
      "question": "ある人は、自分の功績を人々が認めることを大事にしている。",
      "reason": "15歳1位、18歳合格で成果認められ喜び、9歳努力報われ。",
      "answer": 5
    },
    {
      "question": "ある人は、決して屈辱を与えられないことを大事にしている。",
      "reason": "17歳負け悔しいが成長に転換、屈辱避け優先低。",
      "answer": 2
    },
    {
      "question": "ある人は、自分の国がすべての脅威から自国を守ることを大事にしている。",
      "reason": "国防なし。",
      "answer": 2
    },
    {
      "question": "ある人は、決して人を怒らせないことを大事にしている。",
      "reason": "12歳絶交後悔あるが、徹底せず。",
      "answer": 3
    },
    {
      "question": "ある人は、たとえ自分の知らない人であっても、誰もが公正に扱われることを大事にしている。",
      "reason": "公正社会観なし。",
      "answer": 2
    },
    {
      "question": "ある人は、いかなる危険も避けることを大事にしている。",
      "reason": "危険避けより挑戦（一人暮らし、テニス努力）。",
      "answer": 2
    },
    {
      "question": "ある人は、今あるものに満足し、それ以上を求めないことを大事にしている。",
      "reason": "野心・努力で上を目指す（勉強、テニス）。",
      "answer": 1
    },
    {
      "question": "ある人は、すべての友人や家族が自分に絶対の信頼を寄せられることを大事にしている。",
      "reason": "11歳友達絆続き、信頼重視。",
      "answer": 6
    },
    {
      "question": "ある人は、やることを自分で自由に選択できることを大事にしている。",
      "reason": "自立・人生自決強い（18歳、21歳）。",
      "answer": 6
    },
    {
      "question": "ある人は、たとえ自分と意見が反対の立場の人であっても、その人を受け入れることを大事にしている。",
      "reason": "コミュニケーション学びあるが、女子苦手残るなど限定的寛容。",
      "answer": 3
    }
  ],
  "give_pvq_3": [
    {
      "question": "ある人は、自分なりの意見を形作ることを大事にしている。",
      "reason": "21歳のエピソードで大学に行かなくなり留年したが、学びなおしをし、自分の人生を見つめなおす良いきっかけになったため、自分なりの意見を形成する自立した考え方を大事にしている。",
      "answer": 6
    },
    {
      "question": "ある人は、自分の国が安全で安定していることを大事にしている。",
      "reason": "人生体験に国や安全に関するエピソードがなく、個人レベルの努力や人間関係に焦点が当たっているため、似ていない。",
      "answer": 2
    },
    {
      "question": "ある人は、楽しい時間を過ごすことを大事にしている。",
      "reason": "19歳で大学の友達と九州旅行に行き温泉が思い出、20歳でゲーム趣味に出会い共有の素晴らしさを学んだため、楽しい時間を大事にしている。",
      "answer": 5
    },
    {
      "question": "ある人は、人を困らせないことを大事にしている。",
      "reason": "12歳で友人と絶交し言い過ぎを後悔したため、人を困らせないコミュニケーションを学んだが、絶対的ではない。",
      "answer": 4
    },
    {
      "question": "ある人は、社会の中で弱く傷つきやすい人々が守られることを大事にしている。",
      "reason": "社会的な弱者保護のエピソードはなく、個人体験中心のため似ていない。",
      "answer": 2
    },
    {
      "question": "ある人は、自分が言った通りに人が動くことを大事にしている。",
      "reason": "人間関係で挫折が多く、支配欲を示すエピソードがないため似ていない。",
      "answer": 1
    },
    {
      "question": "ある人は、自分が他の人より価値があるとは決して考えないことを大事にしている。",
      "reason": "15歳で学年1位になり努力の成果を実感したが、謙虚さを強調するエピソードは少ない。",
      "answer": 3
    },
    {
      "question": "ある人は、自然を大切にすることを大事にしている。",
      "reason": "自然に関するエピソードがなく、ペットの猫（14歳）のみで自然全体ではない。",
      "answer": 2
    },
    {
      "question": "ある人は、誰にも恥をかかされないことを大事にしている。",
      "reason": "挫折体験（11歳振られ、17歳負け）で恥を乗り越え成長したため、似ていない。",
      "answer": 2
    },
    {
      "question": "ある人は、いつも何か新しくやる事を探すことを大事にしている。",
      "reason": "20歳でゲームという新趣味に出会い、19歳旅行など新しい経験を楽しんだため、ある程度似ている。",
      "answer": 4
    },
    {
      "question": "ある人は、親しい人の世話をすることを大事にしている。",
      "reason": "14歳猫の死で大切なものを後悔し、11歳男友達の絆を深めたため、親しい人を大事にする。",
      "answer": 5
    },
    {
      "question": "ある人は、お金がもたらす権力を手に入れることを大事にしている。",
      "reason": "お金や権力のエピソードなし、努力と人間関係中心。",
      "answer": 1
    },
    {
      "question": "ある人は、病気を避け、健康を守ることをとても大事にしている。",
      "reason": "健康関連の言及なく、努力や精神的な成長中心。",
      "answer": 2
    },
    {
      "question": "ある人は、あらゆる人達や集団に対して寛容であることを大事にしている。",
      "reason": "女子苦手（11歳）や絶交（12歳）で人間関係難があったが、学び成長した程度。",
      "answer": 3
    },
    {
      "question": "ある人は、規則や規定を決して破らないことを大事にしている。",
      "reason": "21歳大学行かず留年したが規則破りではない、努力遵守型。",
      "answer": 3
    },
    {
      "question": "ある人は、自分の人生は自分で決断するということを大事にしている。",
      "reason": "18歳一人暮らしで自立、21歳人生見つめ直しのため、自立を大事に。",
      "answer": 6
    },
    {
      "question": "ある人は、人生において野心をもつことを大事にしている。",
      "reason": "15歳学年1位、18歳大学合格、17歳勝ちにこだわるようになり努力のサイクル。",
      "answer": 6
    },
    {
      "question": "ある人は、伝統的な価値観や物の考え方を持ち続けることを大事にしている。",
      "reason": "変化と成長（勉強好きに、勝ちこだわり）が多く、伝統言及なし。",
      "answer": 2
    },
    {
      "question": "ある人は、知り合いから絶対の信頼を置かれることを大事にしている。",
      "reason": "11歳男友達絆深く今も続く、信頼される友人重視。",
      "answer": 5
    },
    {
      "question": "ある人は、裕福であることを大事にしている。",
      "reason": "裕福さ言及なし。",
      "answer": 1
    },
    {
      "question": "ある人は、自然を守るための活動に参加することを大事にしている。",
      "reason": "自然活動なし。",
      "answer": 1
    },
    {
      "question": "ある人は、人を決して苛立たせないことを大事にしている。",
      "reason": "12歳絶交で後悔したが、絶対ではない。",
      "answer": 3
    },
    {
      "question": "ある人は、自分の考えを確立することを大事にしている。",
      "reason": "21歳人生見つめ直し、努力で意見形成。",
      "answer": 5
    },
    {
      "question": "ある人は、世間体を守り続けることを大事にしている。",
      "reason": "挫折乗り越え成長、世間体重視なし。",
      "answer": 2
    },
    {
      "question": "ある人は、自分の大切な人を助けることをとても大事にしている。",
      "reason": "14歳猫後悔、13歳恋愛重要、親しい人重視。",
      "answer": 5
    },
    {
      "question": "ある人は、自分の身が安全で守られていることを大事にしている。",
      "reason": "個人安全言及なし。",
      "answer": 2
    },
    {
      "question": "ある人は、信頼され、頼られる友人となることを大事にしている。",
      "reason": "11歳友達絆、信頼重視。",
      "answer": 6
    },
    {
      "question": "ある人は、人生を刺激的にするようなリスクを負うことを大事にしている。",
      "reason": "努力中心でリスク回避的、18歳一人暮らし程度。",
      "answer": 3
    },
    {
      "question": "ある人は、自分の望むことを他の人にさせる権力をもつことを大事にしている。",
      "reason": "権力欲なし。",
      "answer": 1
    },
    {
      "question": "ある人は、自立して行動を計画することを大事にしている。",
      "reason": "18歳一人暮らしで自立一歩、21歳人生見直し。",
      "answer": 6
    },
    {
      "question": "ある人は、誰も見ていない時でも規則を守ることを大事にしている。",
      "reason": "9歳誰かが見てなくてもいい行い、努力家。",
      "answer": 5
    },
    {
      "question": "ある人は、大きな成功を収めることを大事にしている。",
      "reason": "15歳1位、18歳合格、野心あり。",
      "answer": 6
    },
    {
      "question": "ある人は、家族の習慣や宗教のしきたりに従うことを大事にしている。",
      "reason": "家族習慣言及なし。",
      "answer": 1
    },
    {
      "question": "ある人は、自分とは違う人の言うことに耳を傾け、理解する事を大事にしている。",
      "reason": "コミュニケーション学び（12歳）、女子苦手克服試み。",
      "answer": 4
    },
    {
      "question": "ある人は、市民を守ることができる強い国に住むことを大事にしている。",
      "reason": "国関連なし。",
      "answer": 2
    },
    {
      "question": "ある人は、人生の喜びを味わうことを大事にしている。",
      "reason": "楽しい旅行、ゲーム、恋愛喜び。",
      "answer": 5
    },
    {
      "question": "ある人は、世界のすべての人々が人生において平等な機会をもつことを大事にしている。",
      "reason": "平等言及なし。",
      "answer": 2
    },
    {
      "question": "ある人は、謙虚であることを大事にしている。",
      "reason": "成功体験ありだが後悔多め、謙虚さ少し。",
      "answer": 3
    },
    {
      "question": "ある人は、物事を自分で何とかすることを大事にしている。",
      "reason": "自立、一人暮らし、勉強努力。",
      "answer": 6
    },
    {
      "question": "ある人は、自身の文化に関する伝統的なしきたりを重んじることを大事にしている。",
      "reason": "文化伝統なし。",
      "answer": 1
    },
    {
      "question": "ある人は、周囲の人にやるべきことを指示する立場であることを大事にしている。",
      "reason": "指示欲なし。",
      "answer": 1
    },
    {
      "question": "ある人は、いかなる法律も遵守することを大事にしている。",
      "reason": "法律言及なし、規則少し。",
      "answer": 3
    },
    {
      "question": "ある人は、あらゆる種類の新しい経験をすることを大事にしている。",
      "reason": "旅行、ゲーム新趣味、少し新経験。",
      "answer": 4
    },
    {
      "question": "ある人は、自分の富が分かる高価なものをもつことを大事にしている。",
      "reason": "富なし。",
      "answer": 1
    },
    {
      "question": "ある人は、自然環境を破壊や汚染から守ることを大事にしている。",
      "reason": "自然保護なし。",
      "answer": 1
    },
    {
      "question": "ある人は、あらゆる機会を利用して楽しむことを大事にしている。",
      "reason": "楽しい時間重視。",
      "answer": 5
    },
    {
      "question": "ある人は、自分の大切な人が必要とする全てのことに携わることを大事にしている。",
      "reason": "大切な人後悔から大事に。",
      "answer": 5
    },
    {
      "question": "ある人は、自分の功績を人々が認めることを大事にしている。",
      "reason": "努力報われ神様見てくれた（9歳）、成功体験。",
      "answer": 4
    },
    {
      "question": "ある人は、決して屈辱を与えられないことを大事にしている。",
      "reason": "屈辱乗り越え。",
      "answer": 2
    },
    {
      "question": "ある人は、自分の国がすべての脅威から自国を守ることを大事にしている。",
      "reason": "国安全なし。",
      "answer": 2
    },
    {
      "question": "ある人は、決して人を怒らせないことを大事にしている。",
      "reason": "絶交後悔、少し。",
      "answer": 3
    },
    {
      "question": "ある人は、たとえ自分の知らない人であっても、誰もが公正に扱われることを大事にしている。",
      "reason": "公正言及なし。",
      "answer": 2
    },
    {
      "question": "ある人は、いかなる危険も避けることを大事にしている。",
      "reason": "リスク低め。",
      "answer": 3
    },
    {
      "question": "ある人は、今あるものに満足し、それ以上を求めないことを大事にしている。",
      "reason": "野心努力家、満足せず向上。",
      "answer": 1
    },
    {
      "question": "ある人は、すべての友人や家族が自分に絶対の信頼を寄せられることを大事にしている。",
      "reason": "友達信頼重視。",
      "answer": 6
    },
    {
      "question": "ある人は、やることを自分で自由に選択できることを大事にしている。",
      "reason": "自立、人生自分で。",
      "answer": 6
    },
    {
      "question": "ある人は、たとえ自分と意見が反対の立場の人であっても、その人を受け入れることを大事にしている。",
      "reason": "寛容学び少し。",
      "answer": 3
    }
  ]
}